openapi_client/__init__.py
openapi_client/api_client.py
openapi_client/configuration.py
openapi_client/exceptions.py
openapi_client/model_utils.py
openapi_client/rest.py
openapi_client/api/__init__.py
openapi_client/api/application_api.py
openapi_client/api/channels_api.py
openapi_client/api/function_versions_api.py
openapi_client/api/functions_api.py
openapi_client/api/imports_api.py
openapi_client/api/jobs_api.py
openapi_client/api/messages_api.py
openapi_client/api/runtime_api.py
openapi_client/api/threads_api.py
openapi_client/api/users_api.py
openapi_client/apis/__init__.py
openapi_client/model/__init__.py
openapi_client/model/add_channel_member_request.py
openapi_client/model/api_error.py
openapi_client/model/application_job_resource.py
openapi_client/model/application_resource.py
openapi_client/model/application_sent_system_message_notification_data.py
openapi_client/model/application_settings_properties.py
openapi_client/model/application_settings_resource.py
openapi_client/model/authentication_error.py
openapi_client/model/channel_generic_event_resource.py
openapi_client/model/channel_import.py
openapi_client/model/channel_invite_resource.py
openapi_client/model/channel_membership_import.py
openapi_client/model/channel_membership_resource.py
openapi_client/model/channel_message_mention_properties.py
openapi_client/model/channel_message_mention_properties_all_of.py
openapi_client/model/channel_properties.py
openapi_client/model/channel_properties_patch.py
openapi_client/model/channel_resource.py
openapi_client/model/chat_function_chat_runtime_properties.py
openapi_client/model/chat_function_invocation_resource.py
openapi_client/model/chat_function_resource.py
openapi_client/model/chat_function_version_resource.py
openapi_client/model/chat_runtime_dependency_properties.py
openapi_client/model/chat_runtime_environment_variables_properties.py
openapi_client/model/chat_runtime_properties.py
openapi_client/model/chat_runtime_resource.py
chatkitty_server_side_sdk-1.0.0.dist-info/METADATA
chatkitty_server_side_sdk-1.0.0.dist-info/WHEEL
chatkitty_server_side_sdk-1.0.0.dist-info/top_level.txt
chatkitty_server_side_sdk-1.0.0.dist-info/RECORD
