Metadata-Version: 2.1
Name: chatkitty-server-side-sdk
Version: 1.0.0
Summary: ChatKitty Platform REST API
Home-page: 
Author: chatkitty
Author-email: development@chatkitty.com
License: MIT
Keywords: OpenAPI,OpenAPI-Generator,ChatKitty Platform REST API
Requires-Python: >=3.6
Requires-Dist: urllib3 (>=1.25.3)
Requires-Dist: python-dateutil
